wgse/VERSION.py
wgse/__init__.py
wgse/configuration.py
wgse/main.py
wgse/adapters/__init__.py
wgse/adapters/alignment_map_file_info_adapter.py
wgse/adapters/alignment_stats_adapter.py
wgse/adapters/coverage_stats_adapter.py
wgse/adapters/header_adapter.py
wgse/adapters/index_stats_adapter.py
wgse/adapters/reference_adapter.py
wgse/alignment_map/__init__.py
wgse/alignment_map/alignment_map_file.py
wgse/alignment_map/alignment_map_header.py
wgse/alignment_map/alignment_map_row.py
wgse/alignment_map/alignment_stats_calculator.py
wgse/alignment_map/depth_analyzer.py
wgse/alignment_map/index_stats_calculator.py
wgse/alignment_map/variant_caller.py
wgse/data/__init__.py
wgse/data/alignment_stats.py
wgse/data/build.py
wgse/data/chromosome_name_type.py
wgse/data/coverage_stats.py
wgse/data/file_type.py
wgse/data/gender.py
wgse/data/genome.py
wgse/data/microarray_converter.py
wgse/data/mitochondrial_model.py
wgse/data/mitochondrial_model_type.py
wgse/data/mitochondrial_name_type.py
wgse/data/read_type.py
wgse/data/sequence.py
wgse/data/sequence_type.py
wgse/data/sorting.py
wgse/data/source.py
wgse/data/tabular_data.py
wgse/data/alignment_map/__init__.py
wgse/data/alignment_map/alignment_map_file_info.py
wgse/data/alignment_map/alignment_map_header_metadata.py
wgse/data/alignment_map/alignment_map_header_program.py
wgse/data/alignment_map/alignment_map_header_read_group.py
wgse/data/alignment_map/alignment_map_header_sequence.py
wgse/fasta/__init__.py
wgse/fasta/fasta_letter_counter.py
wgse/fasta/fasta_stats_files.py
wgse/fasta/letter_run.py
wgse/fasta/letter_run_buckets.py
wgse/fasta/letter_run_collection.py
wgse/fasta/reference.py
wgse/fastq/__init__.py
wgse/fastq/fastq_file.py
wgse/files/__init__.py
wgse/files/bgzip.py
wgse/files/decompressor.py
wgse/files/downloader.py
wgse/files/file_type_checker.py
wgse/files/gzip.py
wgse/gui/WGSE-NG.pyproject
wgse/gui/WGSE-NG.pyproject.user
wgse/gui/__init__.py
wgse/gui/form.ui
wgse/gui/main.py
wgse/gui/reference.ui
WGSE_NG-1.0.0a14.dist-info/LICENSE
WGSE_NG-1.0.0a14.dist-info/METADATA
WGSE_NG-1.0.0a14.dist-info/WHEEL
WGSE_NG-1.0.0a14.dist-info/entry_points.txt
WGSE_NG-1.0.0a14.dist-info/top_level.txt
WGSE_NG-1.0.0a14.dist-info/RECORD
