Metadata-Version: 2.1
Name: WGSE-NG
Version: 1.0.0a14
Summary: Whole Genome Sequencing data manipulation tool
Author-email: Multiple <unavailable@wgse-ng.com>
License: MIT License
Project-URL: homepage, https://github.com/WGSE-NG/WGSE-NG
Project-URL: Documentation, https://wgse-ng.readthedocs.io/en/latest/
Project-URL: Repository, https://github.com/WGSE-NG/WGSE-NG
Project-URL: Issues, https://github.com/WGSE-NG/WGSE-NG/issues
Project-URL: Changelog, https://github.com/WGSE-NG/WGSE-NG/releases
Keywords: bioinformatics,genetics,wgs,microarray,science
Classifier: Development Status :: 3 - Alpha
Classifier: Environment :: Console
Classifier: Environment :: X11 Applications :: Qt
Classifier: Environment :: Win32 (MS Windows)
Classifier: Intended Audience :: Developers
Classifier: Intended Audience :: Science/Research
Classifier: License :: OSI Approved :: BSD License
Classifier: License :: OSI Approved :: MIT License
Classifier: Operating System :: OS Independent
Classifier: Programming Language :: Python :: 3.12
Classifier: Topic :: Scientific/Engineering :: Bio-Informatics
License-File: LICENSE
Requires-Dist: setuptools
Requires-Dist: pefile
Requires-Dist: pycurl
Requires-Dist: tqdm
Requires-Dist: google-cloud-storage
Requires-Dist: sphinx
Requires-Dist: pytest
Requires-Dist: pyinstaller
Requires-Dist: PySide6
Requires-Dist: jinja2
Requires-Dist: vcf-parser
Requires-Dist: WGSE-NG-3rd-party
Requires-Dist: sentry-sdk
Requires-Dist: debugpy
Requires-Dist: psutil
Requires-Dist: pydantic
